// converted by version 1.3
// on Tue Jun 14 12:59:36 ICT 2022

.package testt {
	.aid 0x11:0x22:0x33:0x44:0x55;
	.version 1.0;

	.imports {
		0xA0:0x0:0x0:0x0:0x62:0x1:0x1 1.3;		//javacard/framework
		0xA0:0x0:0x0:0x0:0x62:0x2:0x1 1.3;		//javacardx/crypto
		0xA0:0x0:0x0:0x0:0x62:0x1:0x2 1.3;		//javacard/security
		0xA0:0x0:0x0:0x0:0x62:0x0:0x1 1.0;		//java/lang
	}

	.applet {
		0x11:0x22:0x33:0x44:0x55:0x0 testt;
	}

	.constantPool {
		// 0
		instanceFieldRef byte[] testt/hoten;
		// 1
		instanceFieldRef byte[] testt/gioitinh;
		// 2
		instanceFieldRef byte[] testt/ngaysinh;
		// 3
		instanceFieldRef byte[] testt/quequan;
		// 4
		instanceFieldRef byte[] testt/sodienthoai;
		// 5
		instanceFieldRef byte[] testt/pin;
		// 6
		instanceFieldRef byte[] testt/tempBuffer;
		// 7
		instanceFieldRef byte[] testt/rsaPubKey;
		// 8
		instanceFieldRef byte[] testt/rsaPriKey;
		// 9
		instanceFieldRef byte[] testt/keyrsa;
		// 10
		instanceFieldRef short testt/rsaPubKeyLen;
		// 11
		instanceFieldRef short testt/rsaPriKeyLen;
		// 12
		instanceFieldRef 1.1 testt/rsaCipher;
		// 13
		instanceFieldRef byte[] testt/aesKey;
		// 14
		instanceFieldRef byte testt/aesKeyLen;
		// 15
		instanceFieldRef 1.1 testt/aesEcbCipher;
		// 16
		instanceFieldRef 2.20 testt/tempAesKey1;
		// 17
		staticFieldRef short testt/counter;
		// 18
		staticMethodRef 1.1.0(BZ)Ljavacardx/crypto/Cipher;;		// javacardx/crypto/Cipher.getInstance(BZ)Ljavacardx/crypto/Cipher;
			.descriptor	Ljavacardx/crypto/Cipher;	1.1;

		// 19
		virtualMethodRef 0.3.1()V;		// register()V
		// 20
		staticMethodRef testt/<init>()V;
		// 21
		classRef testt;
		// 22
		staticMethodRef 0.8.18()V;		// javacard/framework/JCSystem.requestObjectDeletion()V
		// 23
		virtualMethodRef 0.3.3()Z;		// selectingApplet()Z
		// 24
		virtualMethodRef 0.10.1()[B;		// getBuffer()[B
		// 25
		virtualMethodRef 0.10.6()S;		// setIncomingAndReceive()S
		// 26
		staticMethodRef testt/init_kh(Ljavacard/framework/APDU;S)V;
			.descriptor	Ljavacard/framework/APDU;	0.10;

		// 27
		staticMethodRef testt/get_pin(Ljavacard/framework/APDU;)V;
			.descriptor	Ljavacard/framework/APDU;	0.10;

		// 28
		staticMethodRef testt/get_info_kh(Ljavacard/framework/APDU;)V;
			.descriptor	Ljavacard/framework/APDU;	0.10;

		// 29
		staticMethodRef testt/checkcard(Ljavacard/framework/APDU;)V;
			.descriptor	Ljavacard/framework/APDU;	0.10;

		// 30
		staticMethodRef testt/clear_card(Ljavacard/framework/APDU;)V;
			.descriptor	Ljavacard/framework/APDU;	0.10;

		// 31
		staticMethodRef testt/check_pin(Ljavacard/framework/APDU;S)V;
			.descriptor	Ljavacard/framework/APDU;	0.10;

		// 32
		staticMethodRef testt/unblockcard(Ljavacard/framework/APDU;)V;
			.descriptor	Ljavacard/framework/APDU;	0.10;

		// 33
		staticMethodRef 0.7.1(S)V;		// javacard/framework/ISOException.throwIt(S)V
		// 34
		virtualMethodRef 0.10.7()S;		// setOutgoing()S
		// 35
		virtualMethodRef 0.10.9(S)V;		// setOutgoingLength(S)V
		// 36
		staticFieldRef boolean testt/block_card;
		// 37
		staticFieldRef byte[] testt/abc;
		// 38
		virtualMethodRef 0.10.5([BSS)V;		// sendBytesLong([BSS)V
		// 39
		staticMethodRef 0.16.0([BS[BSS)B;		// javacard/framework/Util.arrayCompare([BS[BSS)B
		// 40
		staticFieldRef short testt/len_hoten;
		// 41
		staticFieldRef short testt/len_ngaysinh;
		// 42
		staticFieldRef short testt/len_gioitinh;
		// 43
		staticFieldRef short testt/len_quequan;
		// 44
		staticFieldRef short testt/len_sodienthoai;
		// 45
		staticFieldRef short testt/len_pin;
		// 46
		staticMethodRef 0.16.3([BSSB)S;		// javacard/framework/Util.arrayFillNonAtomic([BSSB)S
		// 47
		staticMethodRef 0.16.1([BS[BSS)S;		// javacard/framework/Util.arrayCopy([BS[BSS)S
		// 48
		virtualMethodRef 0.10.8(SS)V;		// setOutgoingAndSend(SS)V
		// 49
		staticMethodRef testt/doAesCipher(Ljavacard/framework/APDU;[BSB[B)V;
			.descriptor	Ljavacard/framework/APDU;	0.10;

		// 50
		staticMethodRef testt/doRSACipher2(Ljavacard/framework/APDU;[BS)V;
			.descriptor	Ljavacard/framework/APDU;	0.10;

		// 51
		staticMethodRef testt/genRsaKeyPair(Ljavacard/framework/APDU;)V;
			.descriptor	Ljavacard/framework/APDU;	0.10;

		// 52
		staticMethodRef testt/encrypt_private_key(Ljavacard/framework/APDU;)V;
			.descriptor	Ljavacard/framework/APDU;	0.10;

		// 53
		staticMethodRef testt/decrypt_private_key(Ljavacard/framework/APDU;)V;
			.descriptor	Ljavacard/framework/APDU;	0.10;

		// 54
		staticMethodRef testt/doRSACipher(Ljavacard/framework/APDU;S[BSS)V;
			.descriptor	Ljavacard/framework/APDU;	0.10;

		// 55
		staticMethodRef testt/setAesKey(Ljavacard/framework/APDU;S)V;
			.descriptor	Ljavacard/framework/APDU;	0.10;

		// 56
		staticMethodRef 2.13.0(BSZ)Ljavacard/security/Key;;		// javacard/security/KeyBuilder.buildKey(BSZ)Ljavacard/security/Key;
			.descriptor	Ljavacard/security/Key;	2.0;

		// 57
		classRef 2.9;		// javacard/security/RSAPublicKey
		// 58
		virtualMethodRef 1.1.3(Ljavacard/security/Key;B)V;		// init(Ljavacard/security/Key;B)V
			.descriptor	Ljavacard/security/Key;	2.0;

		// 59
		virtualMethodRef 1.1.1([BSS[BS)S;		// doFinal([BSS[BS)S
		// 60
		classRef 2.8;		// javacard/security/RSAPrivateKey
		// 61
		virtualMethodRef 0.10.4(SS)V;		// sendBytes(SS)V
		// 62
		staticMethodRef 0.16.2([BS[BSS)S;		// javacard/framework/Util.arrayCopyNonAtomic([BS[BSS)S
		// 63
		staticMethodRef testt/getRsaPriKeyComponent(B[BS)S;
		// 64
		classRef 2.12;		// javacard/security/CryptoException
		// 65
		classRef 2.16;		// javacard/security/KeyPair
		// 66
		staticMethodRef 2.16.0(BS)V;		// javacard/security/KeyPair.<init>(BS)V
		// 67
		virtualMethodRef 2.16.1()V;		// genKeyPair()V
		// 68
		staticMethodRef 0.8.1()V;		// javacard/framework/JCSystem.beginTransaction()V
		// 69
		staticMethodRef 0.8.2()V;		// javacard/framework/JCSystem.commitTransaction()V
		// 70
		virtualMethodRef 2.16.3()Ljavacard/security/PublicKey;;		// getPublic()Ljavacard/security/PublicKey;
			.descriptor	Ljavacard/security/PublicKey;	2.3;

		// 71
		virtualMethodRef 2.16.2()Ljavacard/security/PrivateKey;;		// getPrivate()Ljavacard/security/PrivateKey;
			.descriptor	Ljavacard/security/PrivateKey;	2.2;

		// 72
		virtualMethodRef 2.12.1()S;		// getReason()S
		// 73
		staticMethodRef 0.8.13(SB)[B;		// javacard/framework/JCSystem.makeTransientByteArray(SB)[B
		// 74
		classRef 2.20;		// javacard/security/AESKey
		// 75
		staticMethodRef 0.3.0()V;		// javacard/framework/Applet.<init>()V
	}

	.class public testt 0 extends 0.3 {		// extends javacard/framework/Applet

		.fields {
			private final byte[] hoten 0;		// [B
			private final byte[] ngaysinh 1;		// [B
			private final byte[] gioitinh 2;		// [B
			private final byte[] quequan 3;		// [B
			private final byte[] sodienthoai 4;		// [B
			private final byte[] pin 5;		// [B
			private final byte[] tempBuffer 6;		// [B
			private final byte[] aesKey 7;		// [B
			private final byte[] rsaPubKey 8;		// [B
			private final byte[] rsaPriKey 9;		// [B
			private final byte[] keyrsa 10;		// [B
			private 1.1 aesEcbCipher 11;		// Ljavacardx/crypto/Cipher;
			private 1.1 rsaCipher 12;		// Ljavacardx/crypto/Cipher;
			private 2.20 tempAesKey1 13;		// Ljavacard/security/AESKey;
			private byte aesKeyLen 14;		// B
			private short rsaPubKeyLen 15;		// S
			private short rsaPriKeyLen 16;		// S
			private static short len_hoten;		// S
			private static short len_ngaysinh;		// S
			private static short len_gioitinh;		// S
			private static short len_quequan;		// S
			private static short len_sodienthoai;		// S
			private static short len_pin;		// S
			private static short counter;		// S
			private static final byte INS_INIT_KH = 16;		// B
			private static final byte UNBLOCK_CARD = 17;		// B
			private static final byte INS_GETPIN = 18;		// B
			private static final byte INS_GETINFO = 19;		// B
			private static final byte CKECK_CARD = 20;		// B
			private static final byte CLEAR_CARD = 21;		// B
			private static final byte CHECK_PIN = 22;		// B
			private static final byte INS_SETIMG = 23;		// B
			private static final byte INS_GETIMG = 24;		// B
			private static final byte INS_NAPTIEN = 25;		// B
			private static final byte INS_THANHTOAN = 32;		// B
			private static final byte INS_SODU = 33;		// B
			private static boolean block_card;		// Z
			private static final byte[] abc = {58,0,1};		// [B
			private static final short SW_REFERENCE_DATA_NOT_FOUND = 27272;		// S
		}

		.publicMethodTable 7 {
			equals(Ljava/lang/Object;)Z;
			register()V;
			register([BSB)V;
			selectingApplet()Z;
			deselect()V;
			getShareableInterfaceObject(Ljavacard/framework/AID;B)Ljavacard/framework/Shareable;;
			select()Z;
			process(Ljavacard/framework/APDU;)V;
		}

		.packageMethodTable 0 {
		}

		.method public static install([BSB)V 0 {
			.stack 2;
			.locals 0;

				L0:	new 21;		// testt/testt
					dup;
					invokespecial 20;		// testt/testt.<init>()V
					pop;
					return;
		}

		.method public <init>()V 1 {
			.stack 3;
			.locals 0;

				L0:	aload_0;
					invokespecial 75;		// javacard/framework/Applet.<init>()V
					aload_0;
					invokevirtual 19;		// register()V
					aload_0;
					bspush 64;
					newarray 11;
					putfield_a 0;		// reference testt/testt.hoten
					aload_0;
					bspush 64;
					newarray 11;
					putfield_a 1;		// reference testt/testt.gioitinh
					aload_0;
					bspush 64;
					newarray 11;
					putfield_a 2;		// reference testt/testt.ngaysinh
					aload_0;
					bspush 64;
					newarray 11;
					putfield_a 3;		// reference testt/testt.quequan
					aload_0;
					bspush 64;
					newarray 11;
					putfield_a 4;		// reference testt/testt.sodienthoai
					aload_0;
					bspush 18;
					newarray 11;
					putfield_a 5;		// reference testt/testt.pin
					aload_0;
					sspush 256;
					sconst_2;
					invokestatic 73;		// javacard/framework/JCSystem.makeTransientByteArray(SB)[B
					putfield_a 6;		// reference testt/testt.tempBuffer
					aload_0;
					sspush 128;
					newarray 11;
					putfield_a 7;		// reference testt/testt.rsaPubKey
					aload_0;
					sspush 128;
					newarray 11;
					putfield_a 8;		// reference testt/testt.rsaPriKey
					aload_0;
					sspush 128;
					newarray 11;
					putfield_a 9;		// reference testt/testt.keyrsa
					aload_0;
					sconst_0;
					putfield_s 10;		// short testt/testt.rsaPubKeyLen
					aload_0;
					sconst_0;
					putfield_s 11;		// short testt/testt.rsaPriKeyLen
					sconst_3;
					putstatic_s 17;		// short testt/testt.counter
					aload_0;
					bspush 10;
					sconst_0;
					invokestatic 18;		// javacardx/crypto/Cipher.getInstance(BZ)Ljavacardx/crypto/Cipher;
					putfield_a 12;		// reference testt/testt.rsaCipher
					aload_0;
					bspush 16;
					newarray 11;
					putfield_a 13;		// reference testt/testt.aesKey
					aload_0;
					sconst_0;
					putfield_b 14;		// byte testt/testt.aesKeyLen
					invokestatic 22;		// javacard/framework/JCSystem.requestObjectDeletion()V
					return;
		}

		.method public process(Ljavacard/framework/APDU;)V 7 {
			.stack 3;
			.locals 2;

			.descriptor	Ljavacard/framework/APDU;	0.10;

				L0:	aload_0;
					invokevirtual 23;		// selectingApplet()Z
					ifeq L2;
				L1:	return;
				L2:	aload_1;
					invokevirtual 24;		// getBuffer()[B
					astore_2;
				L3:	aload_1;
					invokevirtual 25;		// setIncomingAndReceive()S
					sstore_3;
				L4:	aload_2;
					sconst_1;
					baload;
					stableswitch L12 16 22 L5 L11 L6 L7 L8 L9 L10;
				L5:	aload_0;
					aload_1;
					sload_3;
					invokespecial 26;		// testt/testt.init_kh(Ljavacard/framework/APDU;S)V
					goto L13;
				L6:	aload_0;
					aload_1;
					invokespecial 27;		// testt/testt.get_pin(Ljavacard/framework/APDU;)V
					goto L13;
				L7:	aload_0;
					aload_1;
					invokespecial 28;		// testt/testt.get_info_kh(Ljavacard/framework/APDU;)V
					goto L13;
				L8:	aload_0;
					aload_1;
					invokespecial 29;		// testt/testt.checkcard(Ljavacard/framework/APDU;)V
					goto L13;
				L9:	aload_0;
					aload_1;
					invokespecial 30;		// testt/testt.clear_card(Ljavacard/framework/APDU;)V
					goto L13;
				L10:	aload_0;
					aload_1;
					sload_3;
					invokespecial 31;		// testt/testt.check_pin(Ljavacard/framework/APDU;S)V
					goto L13;
				L11:	aload_0;
					aload_1;
					invokespecial 32;		// testt/testt.unblockcard(Ljavacard/framework/APDU;)V
					goto L13;
				L12:	sspush 27904;
					invokestatic 33;		// javacard/framework/ISOException.throwIt(S)V
				L13:	return;
		}

		.method private checkcard(Ljavacard/framework/APDU;)V {
			.stack 4;
			.locals 1;

			.descriptor	Ljavacard/framework/APDU;	0.10;

				L0:	aload_1;
					invokevirtual 24;		// getBuffer()[B
					astore_2;
				L1:	aload_1;
					invokevirtual 34;		// setOutgoing()S
					pop;
					aload_1;
					sconst_1;
					invokevirtual 35;		// setOutgoingLength(S)V
					getstatic_b 36;		// boolean testt/testt.block_card
					sconst_1;
					if_scmpne L3;
				L2:	aload_1;
					getstatic_a 37;		// reference testt/testt.abc
					sconst_2;
					sconst_1;
					invokevirtual 38;		// sendBytesLong([BSS)V
					goto L4;
				L3:	aload_1;
					getstatic_a 37;		// reference testt/testt.abc
					sconst_1;
					sconst_1;
					invokevirtual 38;		// sendBytesLong([BSS)V
				L4:	return;
		}

		.method private check_pin(Ljavacard/framework/APDU;S)V {
			.stack 5;
			.locals 1;

			.descriptor	Ljavacard/framework/APDU;	0.10;

				L0:	aload_1;
					invokevirtual 24;		// getBuffer()[B
					astore_3;
				L1:	aload_1;
					invokevirtual 34;		// setOutgoing()S
					pop;
					aload_1;
					sconst_1;
					invokevirtual 35;		// setOutgoingLength(S)V
					aload_3;
					sconst_5;
					getfield_a_this 5;		// reference testt/testt.pin
					sconst_0;
					sload_2;
					invokestatic 39;		// javacard/framework/Util.arrayCompare([BS[BSS)B
					ifne L3;
				L2:	aload_1;
					getstatic_a 37;		// reference testt/testt.abc
					sconst_1;
					sconst_1;
					invokevirtual 38;		// sendBytesLong([BSS)V
					goto L6;
				L3:	getstatic_s 17;		// short testt/testt.counter
					sconst_1;
					ssub;
					putstatic_s 17;		// short testt/testt.counter
					getstatic_s 17;		// short testt/testt.counter
					ifne L5;
				L4:	sconst_1;
					putstatic_b 36;		// boolean testt/testt.block_card
				L5:	aload_1;
					getstatic_a 37;		// reference testt/testt.abc
					sconst_2;
					sconst_1;
					invokevirtual 38;		// sendBytesLong([BSS)V
				L6:	return;
		}

		.method private unblockcard(Ljavacard/framework/APDU;)V {
			.stack 1;
			.locals 0;

			.descriptor	Ljavacard/framework/APDU;	0.10;

				L0:	sconst_3;
					putstatic_s 17;		// short testt/testt.counter
					sconst_0;
					putstatic_b 36;		// boolean testt/testt.block_card
					return;
		}

		.method private clear_card(Ljavacard/framework/APDU;)V {
			.stack 4;
			.locals 0;

			.descriptor	Ljavacard/framework/APDU;	0.10;

				L0:	sconst_0;
					putstatic_s 40;		// short testt/testt.len_hoten
					sconst_0;
					putstatic_s 41;		// short testt/testt.len_ngaysinh
					sconst_0;
					putstatic_s 42;		// short testt/testt.len_gioitinh
					sconst_0;
					putstatic_s 43;		// short testt/testt.len_quequan
					sconst_0;
					putstatic_s 44;		// short testt/testt.len_sodienthoai
					sconst_0;
					putstatic_s 45;		// short testt/testt.len_pin
					getfield_a_this 0;		// reference testt/testt.hoten
					sconst_0;
					bspush 64;
					sconst_0;
					invokestatic 46;		// javacard/framework/Util.arrayFillNonAtomic([BSSB)S
					pop;
					getfield_a_this 2;		// reference testt/testt.ngaysinh
					sconst_0;
					bspush 64;
					sconst_0;
					invokestatic 46;		// javacard/framework/Util.arrayFillNonAtomic([BSSB)S
					pop;
					getfield_a_this 1;		// reference testt/testt.gioitinh
					sconst_0;
					bspush 64;
					sconst_0;
					invokestatic 46;		// javacard/framework/Util.arrayFillNonAtomic([BSSB)S
					pop;
					getfield_a_this 3;		// reference testt/testt.quequan
					sconst_0;
					bspush 64;
					sconst_0;
					invokestatic 46;		// javacard/framework/Util.arrayFillNonAtomic([BSSB)S
					pop;
					getfield_a_this 4;		// reference testt/testt.sodienthoai
					sconst_0;
					bspush 64;
					sconst_0;
					invokestatic 46;		// javacard/framework/Util.arrayFillNonAtomic([BSSB)S
					pop;
					getfield_a_this 5;		// reference testt/testt.pin
					sconst_0;
					bspush 18;
					sconst_0;
					invokestatic 46;		// javacard/framework/Util.arrayFillNonAtomic([BSSB)S
					pop;
					getfield_a_this 8;		// reference testt/testt.rsaPriKey
					sconst_0;
					sspush 128;
					sconst_0;
					invokestatic 46;		// javacard/framework/Util.arrayFillNonAtomic([BSSB)S
					pop;
					getfield_a_this 7;		// reference testt/testt.rsaPubKey
					sconst_0;
					sspush 128;
					sconst_0;
					invokestatic 46;		// javacard/framework/Util.arrayFillNonAtomic([BSSB)S
					pop;
					getfield_a_this 13;		// reference testt/testt.aesKey
					sconst_0;
					bspush 16;
					sconst_0;
					invokestatic 46;		// javacard/framework/Util.arrayFillNonAtomic([BSSB)S
					pop;
					return;
		}

		.method private get_pin(Ljavacard/framework/APDU;)V {
			.stack 5;
			.locals 1;

			.descriptor	Ljavacard/framework/APDU;	0.10;

				L0:	aload_1;
					invokevirtual 24;		// getBuffer()[B
					astore_2;
				L1:	getfield_a_this 5;		// reference testt/testt.pin
					sconst_0;
					aload_2;
					sconst_0;
					bspush 18;
					invokestatic 47;		// javacard/framework/Util.arrayCopy([BS[BSS)S
					pop;
					aload_1;
					sconst_0;
					bspush 18;
					invokevirtual 48;		// setOutgoingAndSend(SS)V
					return;
		}

		.method private get_info_kh(Ljavacard/framework/APDU;)V {
			.stack 6;
			.locals 1;

			.descriptor	Ljavacard/framework/APDU;	0.10;

				L0:	aload_1;
					invokevirtual 24;		// getBuffer()[B
					astore_2;
				L1:	aload_1;
					invokevirtual 34;		// setOutgoing()S
					pop;
					aload_1;
					sspush 200;
					invokevirtual 35;		// setOutgoingLength(S)V
					aload_2;
					sconst_0;
					bspush 58;
					bastore;
					aload_0;
					aload_1;
					getfield_a_this 8;		// reference testt/testt.rsaPriKey
					sspush 128;
					sconst_1;
					getfield_a_this 9;		// reference testt/testt.keyrsa
					invokespecial 49;		// testt/testt.doAesCipher(Ljavacard/framework/APDU;[BSB[B)V
					aload_0;
					aload_1;
					getfield_a_this 0;		// reference testt/testt.hoten
					bspush 64;
					invokespecial 50;		// testt/testt.doRSACipher2(Ljavacard/framework/APDU;[BS)V
					aload_0;
					aload_1;
					getfield_a_this 2;		// reference testt/testt.ngaysinh
					bspush 64;
					invokespecial 50;		// testt/testt.doRSACipher2(Ljavacard/framework/APDU;[BS)V
					aload_0;
					aload_1;
					getfield_a_this 1;		// reference testt/testt.gioitinh
					bspush 64;
					invokespecial 50;		// testt/testt.doRSACipher2(Ljavacard/framework/APDU;[BS)V
					aload_0;
					aload_1;
					getfield_a_this 3;		// reference testt/testt.quequan
					bspush 64;
					invokespecial 50;		// testt/testt.doRSACipher2(Ljavacard/framework/APDU;[BS)V
					aload_0;
					aload_1;
					getfield_a_this 4;		// reference testt/testt.sodienthoai
					bspush 64;
					invokespecial 50;		// testt/testt.doRSACipher2(Ljavacard/framework/APDU;[BS)V
					return;
		}

		.method private init_kh(Ljavacard/framework/APDU;S)V {
			.stack 7;
			.locals 7;

			.descriptor	Ljavacard/framework/APDU;	0.10;

				L0:	sconst_0;
					dup;
					sstore 7;
				L1:	dup;
					sstore 6;
				L2:	dup;
					sstore 5;
				L3:	dup;
					sstore 4;
				L4:	sstore_3;
				L5:	aload_1;
					invokevirtual 24;		// getBuffer()[B
					astore 8;
				L6:	aload 8;
					sconst_5;
					getfield_a_this 6;		// reference testt/testt.tempBuffer
					sconst_0;
					sload_2;
					invokestatic 47;		// javacard/framework/Util.arrayCopy([BS[BSS)S
					pop;
					sconst_0;
					sstore 9;
				L7:	sload 9;
					sload_2;
					if_scmpge L19;
				L8:	getfield_a_this 6;		// reference testt/testt.tempBuffer
					sload 9;
					baload;
					bspush 46;
					if_scmpne L18;
				L9:	sload_3;
					ifne L11;
				L10:	sload 9;
					sstore_3;
					sload_3;
					putstatic_s 40;		// short testt/testt.len_hoten
					goto L18;
				L11:	sload 4;
					ifne L13;
				L12:	sload 9;
					sstore 4;
					sload 4;
					sload_3;
					ssub;
					sconst_1;
					ssub;
					putstatic_s 41;		// short testt/testt.len_ngaysinh
					goto L18;
				L13:	sload 5;
					ifne L15;
				L14:	sload 9;
					sstore 5;
					sload 5;
					sload 4;
					ssub;
					sconst_1;
					ssub;
					putstatic_s 43;		// short testt/testt.len_quequan
					goto L18;
				L15:	sload 6;
					ifne L17;
				L16:	sload 9;
					sstore 6;
					sload 6;
					sload 5;
					ssub;
					sconst_1;
					ssub;
					putstatic_s 42;		// short testt/testt.len_gioitinh
					goto L18;
				L17:	sload 9;
					sstore 7;
					sload 7;
					sload 6;
					ssub;
					sconst_1;
					ssub;
					putstatic_s 44;		// short testt/testt.len_sodienthoai
					bspush 18;
					putstatic_s 45;		// short testt/testt.len_pin
				L18:	sinc 9 1;
					goto L7;
				L19:	getfield_a_this 6;		// reference testt/testt.tempBuffer
					sconst_0;
					getfield_a_this 0;		// reference testt/testt.hoten
					sconst_0;
					getstatic_s 40;		// short testt/testt.len_hoten
					invokestatic 47;		// javacard/framework/Util.arrayCopy([BS[BSS)S
					pop;
					getfield_a_this 6;		// reference testt/testt.tempBuffer
					sload_3;
					sconst_1;
					sadd;
					getfield_a_this 2;		// reference testt/testt.ngaysinh
					sconst_0;
					getstatic_s 41;		// short testt/testt.len_ngaysinh
					invokestatic 47;		// javacard/framework/Util.arrayCopy([BS[BSS)S
					pop;
					getfield_a_this 6;		// reference testt/testt.tempBuffer
					sload 4;
					sconst_1;
					sadd;
					getfield_a_this 3;		// reference testt/testt.quequan
					sconst_0;
					getstatic_s 43;		// short testt/testt.len_quequan
					invokestatic 47;		// javacard/framework/Util.arrayCopy([BS[BSS)S
					pop;
					getfield_a_this 6;		// reference testt/testt.tempBuffer
					sload 5;
					sconst_1;
					sadd;
					getfield_a_this 1;		// reference testt/testt.gioitinh
					sconst_0;
					getstatic_s 42;		// short testt/testt.len_gioitinh
					invokestatic 47;		// javacard/framework/Util.arrayCopy([BS[BSS)S
					pop;
					getfield_a_this 6;		// reference testt/testt.tempBuffer
					sload 6;
					sconst_1;
					sadd;
					getfield_a_this 4;		// reference testt/testt.sodienthoai
					sconst_0;
					getstatic_s 44;		// short testt/testt.len_sodienthoai
					invokestatic 47;		// javacard/framework/Util.arrayCopy([BS[BSS)S
					pop;
					getfield_a_this 6;		// reference testt/testt.tempBuffer
					sload 7;
					sconst_1;
					sadd;
					getfield_a_this 5;		// reference testt/testt.pin
					sconst_0;
					getstatic_s 45;		// short testt/testt.len_pin
					invokestatic 47;		// javacard/framework/Util.arrayCopy([BS[BSS)S
					pop;
					aload_0;
					aload_1;
					invokespecial 51;		// testt/testt.genRsaKeyPair(Ljavacard/framework/APDU;)V
					aload_0;
					aload_1;
					invokespecial 52;		// testt/testt.encrypt_private_key(Ljavacard/framework/APDU;)V
					aload_0;
					aload_1;
					invokespecial 53;		// testt/testt.decrypt_private_key(Ljavacard/framework/APDU;)V
					aload_0;
					aload_1;
					sconst_0;
					getfield_a_this 0;		// reference testt/testt.hoten
					getstatic_s 40;		// short testt/testt.len_hoten
					sconst_0;
					invokespecial 54;		// testt/testt.doRSACipher(Ljavacard/framework/APDU;S[BSS)V
					aload_0;
					aload_1;
					sconst_0;
					getfield_a_this 2;		// reference testt/testt.ngaysinh
					getstatic_s 41;		// short testt/testt.len_ngaysinh
					sconst_0;
					invokespecial 54;		// testt/testt.doRSACipher(Ljavacard/framework/APDU;S[BSS)V
					aload_0;
					aload_1;
					sconst_0;
					getfield_a_this 3;		// reference testt/testt.quequan
					getstatic_s 43;		// short testt/testt.len_quequan
					sconst_0;
					invokespecial 54;		// testt/testt.doRSACipher(Ljavacard/framework/APDU;S[BSS)V
					aload_0;
					aload_1;
					sconst_0;
					getfield_a_this 1;		// reference testt/testt.gioitinh
					getstatic_s 42;		// short testt/testt.len_gioitinh
					sconst_0;
					invokespecial 54;		// testt/testt.doRSACipher(Ljavacard/framework/APDU;S[BSS)V
					aload_0;
					aload_1;
					sconst_0;
					getfield_a_this 4;		// reference testt/testt.sodienthoai
					getstatic_s 44;		// short testt/testt.len_sodienthoai
					sconst_0;
					invokespecial 54;		// testt/testt.doRSACipher(Ljavacard/framework/APDU;S[BSS)V
					aload_0;
					aload_1;
					sconst_1;
					getfield_a_this 0;		// reference testt/testt.hoten
					getstatic_s 40;		// short testt/testt.len_hoten
					sconst_0;
					invokespecial 54;		// testt/testt.doRSACipher(Ljavacard/framework/APDU;S[BSS)V
					getfield_a_this 6;		// reference testt/testt.tempBuffer
					getstatic_s 40;		// short testt/testt.len_hoten
					sconst_1;
					bspush 58;
					invokestatic 46;		// javacard/framework/Util.arrayFillNonAtomic([BSSB)S
					pop;
					aload_0;
					aload_1;
					sconst_1;
					getfield_a_this 2;		// reference testt/testt.ngaysinh
					getstatic_s 41;		// short testt/testt.len_ngaysinh
					getstatic_s 40;		// short testt/testt.len_hoten
					sconst_1;
					sadd;
					invokespecial 54;		// testt/testt.doRSACipher(Ljavacard/framework/APDU;S[BSS)V
					getfield_a_this 6;		// reference testt/testt.tempBuffer
					getstatic_s 40;		// short testt/testt.len_hoten
					getstatic_s 41;		// short testt/testt.len_ngaysinh
					sadd;
					sconst_1;
					sadd;
					sconst_1;
					bspush 58;
					invokestatic 46;		// javacard/framework/Util.arrayFillNonAtomic([BSSB)S
					pop;
					aload_0;
					aload_1;
					sconst_1;
					getfield_a_this 3;		// reference testt/testt.quequan
					getstatic_s 43;		// short testt/testt.len_quequan
					getstatic_s 40;		// short testt/testt.len_hoten
					getstatic_s 41;		// short testt/testt.len_ngaysinh
					sadd;
					sconst_2;
					sadd;
					invokespecial 54;		// testt/testt.doRSACipher(Ljavacard/framework/APDU;S[BSS)V
					getfield_a_this 6;		// reference testt/testt.tempBuffer
					getstatic_s 40;		// short testt/testt.len_hoten
					getstatic_s 41;		// short testt/testt.len_ngaysinh
					sadd;
					getstatic_s 43;		// short testt/testt.len_quequan
					sadd;
					sconst_2;
					sadd;
					sconst_1;
					bspush 58;
					invokestatic 46;		// javacard/framework/Util.arrayFillNonAtomic([BSSB)S
					pop;
					aload_0;
					aload_1;
					sconst_1;
					getfield_a_this 1;		// reference testt/testt.gioitinh
					getstatic_s 42;		// short testt/testt.len_gioitinh
					getstatic_s 40;		// short testt/testt.len_hoten
					getstatic_s 41;		// short testt/testt.len_ngaysinh
					sadd;
					getstatic_s 43;		// short testt/testt.len_quequan
					sadd;
					sconst_3;
					sadd;
					invokespecial 54;		// testt/testt.doRSACipher(Ljavacard/framework/APDU;S[BSS)V
					getfield_a_this 6;		// reference testt/testt.tempBuffer
					getstatic_s 40;		// short testt/testt.len_hoten
					getstatic_s 41;		// short testt/testt.len_ngaysinh
					sadd;
					getstatic_s 43;		// short testt/testt.len_quequan
					sadd;
					getstatic_s 42;		// short testt/testt.len_gioitinh
					sadd;
					sconst_3;
					sadd;
					sconst_1;
					bspush 58;
					invokestatic 46;		// javacard/framework/Util.arrayFillNonAtomic([BSSB)S
					pop;
					aload_0;
					aload_1;
					sconst_1;
					getfield_a_this 4;		// reference testt/testt.sodienthoai
					getstatic_s 44;		// short testt/testt.len_sodienthoai
					getstatic_s 40;		// short testt/testt.len_hoten
					getstatic_s 41;		// short testt/testt.len_ngaysinh
					sadd;
					getstatic_s 43;		// short testt/testt.len_quequan
					sadd;
					getstatic_s 42;		// short testt/testt.len_gioitinh
					sadd;
					sconst_4;
					sadd;
					invokespecial 54;		// testt/testt.doRSACipher(Ljavacard/framework/APDU;S[BSS)V
					getfield_a_this 6;		// reference testt/testt.tempBuffer
					getstatic_s 40;		// short testt/testt.len_hoten
					getstatic_s 41;		// short testt/testt.len_ngaysinh
					sadd;
					getstatic_s 43;		// short testt/testt.len_quequan
					sadd;
					getstatic_s 42;		// short testt/testt.len_gioitinh
					sadd;
					getstatic_s 44;		// short testt/testt.len_sodienthoai
					sadd;
					sconst_4;
					sadd;
					sconst_1;
					bspush 58;
					invokestatic 46;		// javacard/framework/Util.arrayFillNonAtomic([BSSB)S
					pop;
					getfield_a_this 6;		// reference testt/testt.tempBuffer
					sconst_0;
					aload 8;
					sconst_0;
					sload_2;
					invokestatic 47;		// javacard/framework/Util.arrayCopy([BS[BSS)S
					pop;
					aload_1;
					sconst_0;
					sload_2;
					invokevirtual 48;		// setOutgoingAndSend(SS)V
					return;
		}

		.method private encrypt_private_key(Ljavacard/framework/APDU;)V {
			.stack 6;
			.locals 0;

			.descriptor	Ljavacard/framework/APDU;	0.10;

				L0:	aload_0;
					aload_1;
					getstatic_s 45;		// short testt/testt.len_pin
					invokespecial 55;		// testt/testt.setAesKey(Ljavacard/framework/APDU;S)V
					aload_0;
					aload_1;
					getfield_a_this 8;		// reference testt/testt.rsaPriKey
					sspush 128;
					sconst_0;
					getfield_a_this 8;		// reference testt/testt.rsaPriKey
					invokespecial 49;		// testt/testt.doAesCipher(Ljavacard/framework/APDU;[BSB[B)V
					return;
		}

		.method private decrypt_private_key(Ljavacard/framework/APDU;)V {
			.stack 6;
			.locals 0;

			.descriptor	Ljavacard/framework/APDU;	0.10;

				L0:	aload_0;
					aload_1;
					getstatic_s 45;		// short testt/testt.len_pin
					invokespecial 55;		// testt/testt.setAesKey(Ljavacard/framework/APDU;S)V
					aload_0;
					aload_1;
					getfield_a_this 8;		// reference testt/testt.rsaPriKey
					sspush 128;
					sconst_1;
					getfield_a_this 9;		// reference testt/testt.keyrsa
					invokespecial 49;		// testt/testt.doAesCipher(Ljavacard/framework/APDU;[BSB[B)V
					return;
		}

		.method private doRSACipher(Ljavacard/framework/APDU;S[BSS)V {
			.stack 6;
			.locals 5;

			.descriptor	Ljavacard/framework/APDU;	0.10;

				L0:	aload_1;
					invokevirtual 24;		// getBuffer()[B
					astore 6;
				L1:	sspush 512;
					sstore 7;
				L2:	bspush 64;
					sstore 8;
				L3:	sload 4;
					ifgt L5;
				L4:	sspush 26368;
					invokestatic 33;		// javacard/framework/ISOException.throwIt(S)V
				L5:	sload_2;
					ifne L10;
				L6:	sconst_4;
					sload 7;
					sconst_0;
					invokestatic 56;		// javacard/security/KeyBuilder.buildKey(BSZ)Ljavacard/security/Key;
					checkcast 0 57;		// T_CLASSORINTERFACE javacard/security/RSAPublicKey
					astore 9;
				L7:	aload 9;
					getfield_a_this 7;		// reference testt/testt.rsaPubKey
					sconst_0;
					sload 8;
					invokeinterface 4 57 7;		// javacard/security/RSAPublicKey
					aload 9;
					getfield_a_this 7;		// reference testt/testt.rsaPubKey
					sload 8;
					sconst_3;
					invokeinterface 4 57 6;		// javacard/security/RSAPublicKey
					getfield_a_this 12;		// reference testt/testt.rsaCipher
					aload 9;
					sconst_2;
					invokevirtual 58;		// init(Ljavacard/security/Key;B)V
					getfield_a_this 12;		// reference testt/testt.rsaCipher
					aload_3;
					sconst_0;
					sload 4;
					aload 6;
					sconst_0;
					invokevirtual 59;		// doFinal([BSS[BS)S
					sstore 10;
				L8:	aload 6;
					sconst_0;
					aload_3;
					sconst_0;
					sload 10;
					invokestatic 47;		// javacard/framework/Util.arrayCopy([BS[BSS)S
					pop;
				L9:	goto L12;
				L10:	sconst_5;
					sload 7;
					sconst_0;
					invokestatic 56;		// javacard/security/KeyBuilder.buildKey(BSZ)Ljavacard/security/Key;
					checkcast 0 60;		// T_CLASSORINTERFACE javacard/security/RSAPrivateKey
					astore 9;
				L11:	aload 9;
					getfield_a_this 9;		// reference testt/testt.keyrsa
					sconst_0;
					sload 8;
					invokeinterface 4 60 7;		// javacard/security/RSAPrivateKey
					aload 9;
					getfield_a_this 9;		// reference testt/testt.keyrsa
					sload 8;
					sload 8;
					invokeinterface 4 60 6;		// javacard/security/RSAPrivateKey
					getfield_a_this 12;		// reference testt/testt.rsaCipher
					aload 9;
					sconst_1;
					invokevirtual 58;		// init(Ljavacard/security/Key;B)V
					getfield_a_this 12;		// reference testt/testt.rsaCipher
					aload_3;
					sconst_0;
					bspush 64;
					getfield_a_this 6;		// reference testt/testt.tempBuffer
					sload 5;
					invokevirtual 59;		// doFinal([BSS[BS)S
					sstore 10;
				L12:	return;
		}

		.method private doRSACipher2(Ljavacard/framework/APDU;[BS)V {
			.stack 6;
			.locals 5;

			.descriptor	Ljavacard/framework/APDU;	0.10;

				L0:	aload_1;
					invokevirtual 24;		// getBuffer()[B
					astore 4;
				L1:	sspush 512;
					sstore 5;
				L2:	bspush 64;
					sstore 6;
				L3:	sconst_5;
					sload 5;
					sconst_0;
					invokestatic 56;		// javacard/security/KeyBuilder.buildKey(BSZ)Ljavacard/security/Key;
					checkcast 0 60;		// T_CLASSORINTERFACE javacard/security/RSAPrivateKey
					astore 7;
				L4:	aload 7;
					getfield_a_this 9;		// reference testt/testt.keyrsa
					sconst_0;
					sload 6;
					invokeinterface 4 60 7;		// javacard/security/RSAPrivateKey
					aload 7;
					getfield_a_this 9;		// reference testt/testt.keyrsa
					sload 6;
					sload 6;
					invokeinterface 4 60 6;		// javacard/security/RSAPrivateKey
					getfield_a_this 12;		// reference testt/testt.rsaCipher
					aload 7;
					sconst_1;
					invokevirtual 58;		// init(Ljavacard/security/Key;B)V
					getfield_a_this 12;		// reference testt/testt.rsaCipher
					aload_2;
					sconst_0;
					sload_3;
					aload 4;
					sconst_0;
					invokevirtual 59;		// doFinal([BSS[BS)S
					sstore 8;
				L5:	aload_1;
					sconst_0;
					sload 8;
					invokevirtual 61;		// sendBytes(SS)V
					aload_1;
					getstatic_a 37;		// reference testt/testt.abc
					sconst_0;
					sconst_1;
					invokevirtual 38;		// sendBytesLong([BSS)V
					return;
		}

		.method private getRsaPubKey(Ljavacard/framework/APDU;S)V {
			.stack 5;
			.locals 3;

			.descriptor	Ljavacard/framework/APDU;	0.10;

				L0:	aload_1;
					invokevirtual 24;		// getBuffer()[B
					astore_3;
				L1:	getfield_s_this 10;		// short testt/testt.rsaPubKeyLen
					ifne L3;
				L2:	sspush 27272;
					invokestatic 33;		// javacard/framework/ISOException.throwIt(S)V
				L3:	bspush 64;
					sstore 4;
				L4:	aload_3;
					sconst_2;
					baload;
					slookupswitch L8 2 0 L5 1 L6;
				L5:	getfield_a_this 7;		// reference testt/testt.rsaPubKey
					sconst_0;
					aload_3;
					sconst_0;
					sload 4;
					invokestatic 62;		// javacard/framework/Util.arrayCopyNonAtomic([BS[BSS)S
					pop;
					aload_1;
					sconst_0;
					sload 4;
					invokevirtual 48;		// setOutgoingAndSend(SS)V
					goto L9;
				L6:	getfield_s_this 10;		// short testt/testt.rsaPubKeyLen
					sload 4;
					ssub;
					sstore 5;
				L7:	getfield_a_this 7;		// reference testt/testt.rsaPubKey
					sload 4;
					aload_3;
					sconst_0;
					sload 5;
					invokestatic 62;		// javacard/framework/Util.arrayCopyNonAtomic([BS[BSS)S
					pop;
					aload_1;
					sconst_0;
					sload 5;
					invokevirtual 48;		// setOutgoingAndSend(SS)V
					goto L9;
				L8:	sspush 27270;
					invokestatic 33;		// javacard/framework/ISOException.throwIt(S)V
				L9:	return;
		}

		.method private getRsaPriKeyComponent(B[BS)S {
			.stack 5;
			.locals 3;

				L0:	getfield_s_this 11;		// short testt/testt.rsaPriKeyLen
					ifne L2;
				L1:	sconst_0;
					sreturn;
				L2:	bspush 64;
					sstore 4;
				L3:	sload_1;
					slookupswitch L8 2 0 L4 1 L7;
				L4:	sconst_0;
					sstore 5;
				L5:	sload 4;
					sstore 6;
				L6:	goto L9;
				L7:	sload 4;
					sstore 5;
					sload 4;
					sstore 6;
					goto L9;
				L8:	sconst_0;
					sreturn;
				L9:	getfield_a_this 8;		// reference testt/testt.rsaPriKey
					sload 5;
					aload_2;
					sload_3;
					sload 6;
					invokestatic 62;		// javacard/framework/Util.arrayCopyNonAtomic([BS[BSS)S
					pop;
					sload 6;
					sreturn;
		}

		.method private getRsaPriKey([BB)V {
			.stack 4;
			.locals 1;

				L0:	aload_0;
					sload_2;
					aload_1;
					sconst_0;
					invokespecial 63;		// testt/testt.getRsaPriKeyComponent(B[BS)S
					sstore_3;
				L1:	sload_3;
					ifne L3;
				L2:	sspush 27272;
					invokestatic 33;		// javacard/framework/ISOException.throwIt(S)V
				L3:	return;
		}

		.method private genRsaKeyPair(Ljavacard/framework/APDU;)V {
			.stack 4;
			.locals 6;

			.descriptor	Ljavacard/framework/APDU;	0.10;

				L0:	aload_1;
					invokevirtual 24;		// getBuffer()[B
					astore_2;
				L1:	new 65;		// javacard/security/KeyPair
					dup;
					sconst_1;
					sspush 512;
					invokespecial 66;		// javacard/security/KeyPair.<init>(BS)V
					astore_3;
				L2:	aload_3;
					invokevirtual 67;		// genKeyPair()V
					invokestatic 68;		// javacard/framework/JCSystem.beginTransaction()V
					aload_0;
					sconst_0;
					putfield_s 10;		// short testt/testt.rsaPubKeyLen
					aload_0;
					sconst_0;
					putfield_s 11;		// short testt/testt.rsaPriKeyLen
					invokestatic 69;		// javacard/framework/JCSystem.commitTransaction()V
					aload_3;
					invokevirtual 70;		// getPublic()Ljavacard/security/PublicKey;
					checkcast 0 57;		// T_CLASSORINTERFACE javacard/security/RSAPublicKey
					astore 4;
				L3:	sconst_0;
					sstore 5;
				L4:	sload 5;
					aload 4;
					getfield_a_this 7;		// reference testt/testt.rsaPubKey
					sload 5;
					invokeinterface 3 57 5;		// javacard/security/RSAPublicKey
					sadd;
					sstore 5;
					sload 5;
					aload 4;
					getfield_a_this 7;		// reference testt/testt.rsaPubKey
					sload 5;
					invokeinterface 3 57 4;		// javacard/security/RSAPublicKey
					sadd;
					sstore 5;
					sconst_0;
					sstore 6;
				L5:	aload_3;
					invokevirtual 71;		// getPrivate()Ljavacard/security/PrivateKey;
					checkcast 0 60;		// T_CLASSORINTERFACE javacard/security/RSAPrivateKey
					astore 7;
				L6:	sload 6;
					aload 7;
					getfield_a_this 8;		// reference testt/testt.rsaPriKey
					sload 6;
					invokeinterface 3 60 5;		// javacard/security/RSAPrivateKey
					sadd;
					sstore 6;
					sload 6;
					aload 7;
					getfield_a_this 8;		// reference testt/testt.rsaPriKey
					sload 6;
					invokeinterface 3 60 4;		// javacard/security/RSAPrivateKey
					sadd;
					sstore 6;
					invokestatic 68;		// javacard/framework/JCSystem.beginTransaction()V
					aload_0;
					sload 5;
					putfield_s 10;		// short testt/testt.rsaPubKeyLen
					aload_0;
					sload 6;
					putfield_s 11;		// short testt/testt.rsaPriKeyLen
					invokestatic 69;		// javacard/framework/JCSystem.commitTransaction()V
				L7:	goto L11;
				L8:	astore_3;
				L9:	aload_3;
					invokevirtual 72;		// getReason()S
					sstore 4;
				L10:	sload 4;
					invokestatic 33;		// javacard/framework/ISOException.throwIt(S)V
				L11:	invokestatic 22;		// javacard/framework/JCSystem.requestObjectDeletion()V
					return;
			.exceptionTable {
				// start_block end_block handler_block catch_type_index
				L1 L7 L8 64;
			}
		}

		.method private setAesKey(Ljavacard/framework/APDU;S)V {
			.stack 5;
			.locals 2;

			.descriptor	Ljavacard/framework/APDU;	0.10;

				L0:	aload_1;
					invokevirtual 24;		// getBuffer()[B
					astore_3;
				L1:	bspush 16;
					sstore 4;
				L2:	sload_2;
					bspush 16;
					if_scmpge L4;
				L3:	sspush 26368;
					invokestatic 33;		// javacard/framework/ISOException.throwIt(S)V
				L4:	invokestatic 68;		// javacard/framework/JCSystem.beginTransaction()V
					getfield_a_this 5;		// reference testt/testt.pin
					sconst_0;
					getfield_a_this 13;		// reference testt/testt.aesKey
					sconst_0;
					bspush 16;
					invokestatic 47;		// javacard/framework/Util.arrayCopy([BS[BSS)S
					pop;
					aload_0;
					sload 4;
					putfield_b 14;		// byte testt/testt.aesKeyLen
					invokestatic 69;		// javacard/framework/JCSystem.commitTransaction()V
					return;
		}

		.method private doAesCipher(Ljavacard/framework/APDU;[BSB[B)V {
			.stack 6;
			.locals 3;

			.descriptor	Ljavacard/framework/APDU;	0.10;

				L0:	aload_1;
					invokevirtual 24;		// getBuffer()[B
					astore 6;
				L1:	aload_0;
					bspush 13;
					sconst_0;
					invokestatic 18;		// javacardx/crypto/Cipher.getInstance(BZ)Ljavacardx/crypto/Cipher;
					putfield_a 15;		// reference testt/testt.aesEcbCipher
					aload_0;
					bspush 15;
					sspush 128;
					sconst_0;
					invokestatic 56;		// javacard/security/KeyBuilder.buildKey(BSZ)Ljavacard/security/Key;
					checkcast 0 74;		// T_CLASSORINTERFACE javacard/security/AESKey
					putfield_a 16;		// reference testt/testt.tempAesKey1
					sload_3;
					ifle L3;
				L2:	sload_3;
					bspush 16;
					srem;
					ifeq L4;
				L3:	sspush 26368;
					invokestatic 33;		// javacard/framework/ISOException.throwIt(S)V
				L4:	getfield_a_this 16;		// reference testt/testt.tempAesKey1
					getfield_a_this 13;		// reference testt/testt.aesKey
					sconst_0;
					invokeinterface 3 74 4;		// javacard/security/AESKey
					sload 4;
					ifne L6;
				L5:	sconst_2;
					goto L7;
				L6:	sconst_1;
				L7:	sstore 7;
				L8:	getfield_a_this 15;		// reference testt/testt.aesEcbCipher
					astore 8;
				L9:	aload 8;
					getfield_a_this 16;		// reference testt/testt.tempAesKey1
					sload 7;
					invokevirtual 58;		// init(Ljavacard/security/Key;B)V
					sload 7;
					ifne L11;
				L10:	aload 8;
					aload_2;
					sconst_0;
					sload_3;
					aload 6;
					sconst_0;
					invokevirtual 59;		// doFinal([BSS[BS)S
					pop;
					aload 6;
					sconst_0;
					aload_2;
					sconst_0;
					sload_3;
					invokestatic 47;		// javacard/framework/Util.arrayCopy([BS[BSS)S
					pop;
					goto L12;
				L11:	aload 8;
					aload_2;
					sconst_0;
					sload_3;
					aload 6;
					sconst_0;
					invokevirtual 59;		// doFinal([BSS[BS)S
					pop;
					aload 6;
					sconst_0;
					aload 5;
					sconst_0;
					sload_3;
					invokestatic 47;		// javacard/framework/Util.arrayCopy([BS[BSS)S
					pop;
				L12:	goto L16;
				L13:	astore 6;
				L14:	aload 6;
					invokevirtual 72;		// getReason()S
					sstore 7;
				L15:	sload 7;
					invokestatic 33;		// javacard/framework/ISOException.throwIt(S)V
				L16:	return;
			.exceptionTable {
				// start_block end_block handler_block catch_type_index
				L0 L12 L13 64;
			}
		}

	}

}
